faultree/__init__.py
faultree/core.py
faultree/data.py
faultree-0.1.0.dist-info/licenses/LICENSE
tests/__init__.py
tests/test_core.py
tests/test_data.py
faultree-0.1.0.dist-info/METADATA
faultree-0.1.0.dist-info/WHEEL
faultree-0.1.0.dist-info/top_level.txt
faultree-0.1.0.dist-info/RECORD
