Metadata-Version: 2.4
Name: faultree
Version: 0.1.0
Summary: Fault tree analysis library
Author: João Mateus Santana
Project-URL: Homepage, https://github.com/jmateusms/faultree
Project-URL: Issues, https://github.com/jmateusms/faultree/issues
Classifier: Programming Language :: Python :: 3
Classifier: Operating System :: OS Independent
Classifier: License :: OSI Approved :: MIT License
Requires-Python: >=3.8
License-File: LICENSE
Dynamic: license-file
